[
  {"pdf_section_id":"1.1","menu_group":"acesso-e-navegacao","menu_group_label":"Acesso e Navegação","route":"/auth/sign-in","doc_slug":"acesso-e-navegacao/acessando-o-sistema","status":"published","title":"Acessando o Sistema","summary":"Realize login com credenciais válidas e acesse o painel inicial com segurança.","tags":["login","acesso","autenticacao"],"permission_hints":["Usuário ativo"],"related":["acesso-e-navegacao/recuperacao-de-senha","acesso-e-navegacao/dashboard-visao-geral"]},
  {"pdf_section_id":"1.2","menu_group":"acesso-e-navegacao","menu_group_label":"Acesso e Navegação","route":"/auth/forgot-password","doc_slug":"acesso-e-navegacao/recuperacao-de-senha","status":"published","title":"Recuperação de Senha","summary":"Recupere o acesso por e-mail e redefina a senha com fluxo seguro.","tags":["senha","acesso","seguranca"],"permission_hints":["Usuário cadastrado"],"related":["acesso-e-navegacao/acessando-o-sistema"]},
  {"pdf_section_id":"1.3","menu_group":"acesso-e-navegacao","menu_group_label":"Acesso e Navegação","route":"/","doc_slug":"acesso-e-navegacao/dashboard-visao-geral","status":"published","title":"Dashboard - Visão Geral","summary":"Entenda indicadores, atalhos e blocos principais do painel inicial.","tags":["dashboard","indicadores","atalhos"],"permission_hints":["Acesso ao dashboard"],"related":["acesso-e-navegacao/menu-lateral","acesso-e-navegacao/busca-rapida-de-modulos"]},
  {"pdf_section_id":"1.4","menu_group":"acesso-e-navegacao","menu_group_label":"Acesso e Navegação","route":"/","doc_slug":"acesso-e-navegacao/menu-lateral","status":"published","title":"Menu Lateral","summary":"Navegue pelos módulos do Integra usando grupos e atalhos do menu.","tags":["menu","navegacao","modulos"],"permission_hints":["Permissões por módulo"],"related":["acesso-e-navegacao/busca-rapida-de-modulos"]},
  {"pdf_section_id":"1.5","menu_group":"acesso-e-navegacao","menu_group_label":"Acesso e Navegação","route":"/","doc_slug":"acesso-e-navegacao/busca-rapida-de-modulos","status":"published","title":"Busca Rápida de Módulos","summary":"Localize páginas e módulos rapidamente pela busca global do sistema.","tags":["busca","produtividade","atalhos"],"permission_hints":["Permissões de leitura"],"related":["acesso-e-navegacao/menu-lateral"]},
  {"pdf_section_id":"1.6","menu_group":"acesso-e-navegacao","menu_group_label":"Acesso e Navegação","route":"/","doc_slug":"acesso-e-navegacao/outros-elementos-da-interface","status":"published","title":"Outros Elementos da Interface","summary":"Use breadcrumb, notificações e perfil para navegação contextual.","tags":["breadcrumb","notificacoes","perfil"],"permission_hints":["Acesso ao sistema"],"related":["acesso-e-navegacao/dashboard-visao-geral"]},
  {"pdf_section_id":"1.7","menu_group":"acesso-e-navegacao","menu_group_label":"Acesso e Navegação","route":"/config/permissions","doc_slug":"acesso-e-navegacao/sistema-de-permissoes","status":"published","title":"Sistema de Permissões","summary":"Compreenda níveis de acesso e impacto das permissões na interface.","tags":["permissoes","seguranca","perfil"],"permission_hints":["Permissão config_permissions"],"related":["administracao/permissoes","acesso-e-navegacao/menu-lateral"]},
  {"pdf_section_id":"1.8","menu_group":"acesso-e-navegacao","menu_group_label":"Acesso e Navegação","route":"/","doc_slug":"acesso-e-navegacao/resolucao-de-problemas-comuns","status":"published","title":"Resolução de Problemas Comuns","summary":"Resolva incidentes frequentes de login, lentidão e módulos indisponíveis.","tags":["suporte","problemas","troubleshooting"],"permission_hints":["Acesso ao sistema"],"related":["operacoes/solicitacoes-de-suporte"]},

  {"pdf_section_id":"2.1","menu_group":"cadastros","menu_group_label":"Cadastros","route":"/customer","doc_slug":"cadastros/clientes","status":"published","title":"Clientes","summary":"Cadastre e mantenha dados de clientes para operações e CRM.","tags":["clientes","cadastro","crm"],"permission_hints":["customer.list"],"related":["crm/clientes","crm/parque-instalado"]},
  {"pdf_section_id":"2.2","menu_group":"cadastros","menu_group_label":"Cadastros","route":"/equipments","doc_slug":"cadastros/catalogo-de-equipamentos-e-categorias","status":"published","title":"Catálogo de Equipamentos e Categorias","summary":"Gerencie catálogo técnico e categorias usadas em estoque e OS.","tags":["equipamentos","categorias","cadastro"],"permission_hints":["equipment.list","equipment.list_category"],"related":["gestao/hub-de-estoque","gestao/historico-de-equipamentos"]},
  {"pdf_section_id":"2.3","menu_group":"cadastros","menu_group_label":"Cadastros","route":"/parts","doc_slug":"cadastros/catalogo-de-pecas","status":"published","title":"Catálogo de Peças","summary":"Mantenha peças com identificação, status e dados de controle.","tags":["pecas","estoque","cadastro"],"permission_hints":["part.list"],"related":["gestao/hub-de-estoque","compras/solicitacoes-de-compra"]},
  {"pdf_section_id":"2.4","menu_group":"cadastros","menu_group_label":"Cadastros","route":"/product","doc_slug":"cadastros/catalogo-de-produtos","status":"published","title":"Catálogo de Produtos","summary":"Registre produtos para venda, estoque e faturamento.","tags":["produtos","comercial","estoque"],"permission_hints":["product.list"],"related":["comercial/pedidos-de-venda","gestao/hub-de-estoque"]},
  {"pdf_section_id":"2.5","menu_group":"cadastros","menu_group_label":"Cadastros","route":"/accessory","doc_slug":"cadastros/acessorios","status":"published","title":"Acessórios","summary":"Cadastre acessórios vinculáveis a equipamentos e contratos.","tags":["acessorios","equipamentos","cadastro"],"permission_hints":["accessory.list"],"related":["gestao/controle-patrimonial"]},
  {"pdf_section_id":"2.6","menu_group":"cadastros","menu_group_label":"Cadastros","route":"/brand","doc_slug":"cadastros/marcas","status":"published","title":"Marcas","summary":"Padronize marcas para catálogo de peças, produtos e equipamentos.","tags":["marcas","padronizacao","cadastro"],"permission_hints":["brand.list"],"related":["cadastros/catalogo-de-produtos"]},
  {"pdf_section_id":"2.7","menu_group":"cadastros","menu_group_label":"Cadastros","route":"/part-family","doc_slug":"cadastros/familias-de-pecas","status":"published","title":"Famílias de Peças","summary":"Organize peças por famílias para busca, filtros e relatórios.","tags":["pecas","familias","classificacao"],"permission_hints":["part_family.list"],"related":["cadastros/catalogo-de-pecas","relatorios/relatorio-de-estoque"]},
  {"pdf_section_id":"2.8","menu_group":"cadastros","menu_group_label":"Cadastros","route":"/supplier","doc_slug":"cadastros/fornecedores","status":"published","title":"Fornecedores","summary":"Cadastre fornecedores e mantenha dados para compras e qualidade.","tags":["fornecedores","compras","qualidade"],"permission_hints":["supplier.list"],"related":["compras/pedidos-de-compra","qualidade/qualificacao-de-fornecedores"]},
  {"pdf_section_id":"2.9","menu_group":"cadastros","menu_group_label":"Cadastros","route":"/labor","doc_slug":"cadastros/mao-de-obra","status":"published","title":"Mão de Obra","summary":"Mantenha tipos de mão de obra usados em OS e orçamento.","tags":["mao-de-obra","os","orcamento"],"permission_hints":["labor.list"],"related":["operacoes/ordem-de-servico","operacoes/orcamentos"]},
  {"pdf_section_id":"2.10","menu_group":"cadastros","menu_group_label":"Cadastros","route":"/instruments","doc_slug":"cadastros/instrumentos","status":"published","title":"Instrumentos","summary":"Gerencie instrumentos usados em qualidade e calibração.","tags":["instrumentos","qualidade","calibracao"],"permission_hints":["quality.instruments_list"],"related":["qualidade/calibracoes"]},
  {"pdf_section_id":"2.11","menu_group":"cadastros","menu_group_label":"Cadastros","route":"/checklist","doc_slug":"cadastros/checklist","status":"published","title":"Checklist","summary":"Crie checklists operacionais para execução técnica padronizada.","tags":["checklist","operacoes","qualidade"],"permission_hints":["checklist.list"],"related":["operacoes/ordem-de-servico"]},
  {"pdf_section_id":"2.12","menu_group":"cadastros","menu_group_label":"Cadastros","route":"/anvisa-registration-status","doc_slug":"cadastros/status-anvisa","status":"published","title":"Status ANVISA","summary":"Configure status regulatórios para produtos e equipamentos.","tags":["anvisa","regulatorio","cadastro"],"permission_hints":["anvisa_registration_status.list"],"related":["cadastros/catalogo-de-produtos"]},

  {"pdf_section_id":"3.1","menu_group":"operacoes","menu_group_label":"Operações","route":"/service-order","doc_slug":"operacoes/ordem-de-servico","status":"published","title":"Ordem de Serviço","summary":"Abra, acompanhe e finalize OS conforme o fluxo operacional.","tags":["os","operacoes","assistencia"],"permission_hints":["service_order.list"],"related":["operacoes/orcamentos","operacoes/agenda-de-manutencao"]},
  {"pdf_section_id":"3.2","menu_group":"operacoes","menu_group_label":"Operações","route":"/budget","doc_slug":"operacoes/orcamentos","status":"published","title":"Orçamentos","summary":"Monte orçamentos, aprove e acompanhe pendências do cliente.","tags":["orcamento","aprovacao","os"],"permission_hints":["budget.list"],"related":["operacoes/ordem-de-servico","financeiro/faturamento"]},
  {"pdf_section_id":"3.3","menu_group":"operacoes","menu_group_label":"Operações","route":"/schedule","doc_slug":"operacoes/agenda-de-manutencao","status":"published","title":"Agenda de Manutenção","summary":"Programe serviços e janelas de manutenção com controle de agenda.","tags":["agenda","manutencao","planejamento"],"permission_hints":["maintenance_schedule.list"],"related":["gestao/agendamentos-de-manutencao"]},
  {"pdf_section_id":"3.4","menu_group":"operacoes","menu_group_label":"Operações","route":"/technical-visit","doc_slug":"operacoes/visitas-tecnicas","status":"published","title":"Visitas Técnicas","summary":"Registre visitas, etapas de atendimento e histórico técnico.","tags":["visitas","campo","atendimento"],"permission_hints":["technical_visit.list"],"related":["operacoes/ordem-de-servico"]},
  {"pdf_section_id":"3.5","menu_group":"operacoes","menu_group_label":"Operações","route":"/support","doc_slug":"operacoes/solicitacoes-de-suporte","status":"published","title":"Solicitações de Suporte","summary":"Abra e acompanhe solicitações de suporte técnico e operacional.","tags":["suporte","tickets","atendimento"],"permission_hints":["support.list"],"related":["acesso-e-navegacao/resolucao-de-problemas-comuns"]},

  {"pdf_section_id":"4.1","menu_group":"crm","menu_group_label":"CRM","route":"/customer","doc_slug":"crm/clientes","status":"published","title":"Clientes no CRM","summary":"Gerencie clientes no contexto comercial e relacionamento contínuo.","tags":["crm","clientes","relacionamento"],"permission_hints":["customer.list"],"related":["cadastros/clientes","crm/solicitacoes-crm"]},
  {"pdf_section_id":"4.2","menu_group":"crm","menu_group_label":"CRM","route":"/crm","doc_slug":"crm/solicitacoes-crm","status":"published","title":"Solicitações CRM","summary":"Registre oportunidades, demandas e evolução de solicitações comerciais.","tags":["crm","solicitacoes","pipeline"],"permission_hints":["crm.list_report"],"related":["crm/clientes","crm/parque-instalado"]},
  {"pdf_section_id":"4.3","menu_group":"crm","menu_group_label":"CRM","route":"/crm/customer-equipment","doc_slug":"crm/parque-instalado","status":"published","title":"Parque Instalado","summary":"Associe equipamentos a clientes e mantenha rastreabilidade instalada.","tags":["parque-instalado","equipamentos","crm"],"permission_hints":["crm.customer_equipment_list_customers"],"related":["gestao/controle-patrimonial","gestao/historico-de-equipamentos"]},

  {"pdf_section_id":"5.1","menu_group":"gestao","menu_group_label":"Gestão","route":"/stock","doc_slug":"gestao/hub-de-estoque","status":"published","title":"Hub de Estoque","summary":"Gerencie estoques de equipamentos, peças e produtos no mesmo hub.","tags":["estoque","hub","lotes"],"permission_hints":["stock.list_part","stock.list_product","stock.list_equipment"],"related":["relatorios/relatorio-de-estoque"]},
  {"pdf_section_id":"5.2","menu_group":"gestao","menu_group_label":"Gestão","route":"/history","doc_slug":"gestao/historico-de-equipamentos","status":"published","title":"Histórico de Equipamentos","summary":"Consulte alterações e rastreabilidade histórica dos equipamentos.","tags":["historico","equipamentos","rastreabilidade"],"permission_hints":["equipment.history_list"],"related":["gestao/controle-patrimonial","crm/parque-instalado"]},
  {"pdf_section_id":"5.3","menu_group":"gestao","menu_group_label":"Gestão","route":"/asset-equipment","doc_slug":"gestao/controle-patrimonial","status":"published","title":"Controle Patrimonial","summary":"Controle movimentações e ciclo de vida de ativos patrimoniais.","tags":["patrimonio","ativos","movimentacao"],"permission_hints":["equipment.show_asset_equipment"],"related":["gestao/historico-de-equipamentos"]},
  {"pdf_section_id":"5.4","menu_group":"gestao","menu_group_label":"Gestão","route":"/contract/maintenance","doc_slug":"gestao/contratos-de-manutencao","status":"published","title":"Contratos de Manutenção","summary":"Cadastre contratos recorrentes e regras de manutenção associadas.","tags":["contratos","manutencao","gestao"],"permission_hints":["maintenance_contract.list"],"related":["gestao/agendamentos-de-manutencao"]},
  {"pdf_section_id":"5.5","menu_group":"gestao","menu_group_label":"Gestão","route":"/contract/rental","doc_slug":"gestao/contratos-de-locacao","status":"published","title":"Contratos de Locação","summary":"Gerencie contratos de locação com itens, prazos e status.","tags":["locacao","contratos","gestao"],"permission_hints":["rental_contract.list"],"related":["gestao/controle-patrimonial"]},
  {"pdf_section_id":"5.6","menu_group":"gestao","menu_group_label":"Gestão","route":"/maintenance-schedule","doc_slug":"gestao/agendamentos-de-manutencao","status":"published","title":"Agendamentos de Manutenção","summary":"Automatize e acompanhe agendamentos vinculados a contratos e ativos.","tags":["agendamento","manutencao","contratos"],"permission_hints":["maintenance_schedule.list"],"related":["operacoes/agenda-de-manutencao","gestao/contratos-de-manutencao"]},

  {"pdf_section_id":"6.1","menu_group":"compras","menu_group_label":"Compras","route":"/purchase/request","doc_slug":"compras/solicitacoes-de-compra","status":"published","title":"Solicitações de Compra","summary":"Solicite itens para reposição e aquisição conforme necessidade operacional.","tags":["compras","solicitacoes","suprimentos"],"permission_hints":["purchase.list_request"],"related":["compras/pedidos-de-compra"]},
  {"pdf_section_id":"6.2","menu_group":"compras","menu_group_label":"Compras","route":"/purchase","doc_slug":"compras/pedidos-de-compra","status":"published","title":"Pedidos de Compra","summary":"Converta solicitações em pedidos e acompanhe status de aquisição.","tags":["compras","pedidos","fornecedores"],"permission_hints":["purchase.list"],"related":["compras/solicitacoes-de-compra","cadastros/fornecedores"]},

  {"pdf_section_id":"7.1","menu_group":"comercial","menu_group_label":"Comercial","route":"/sales-order","doc_slug":"comercial/pedidos-de-venda","status":"published","title":"Pedidos de Venda","summary":"Registre pedidos de venda com itens, impostos e condições comerciais.","tags":["vendas","pedidos","comercial"],"permission_hints":["commercial.sales_order_list"],"related":["financeiro/faturamento","cadastros/catalogo-de-produtos"]},

  {"pdf_section_id":"8.1","menu_group":"financeiro","menu_group_label":"Financeiro","route":"/financial","doc_slug":"financeiro/visao-geral-do-modulo-financeiro","status":"published","title":"Visão Geral do Módulo Financeiro","summary":"Conheça os submódulos financeiros e principais fluxos de trabalho.","tags":["financeiro","visao-geral","modulo"],"permission_hints":["Acesso ao módulo financeiro"],"related":["financeiro/contas-a-receber","financeiro/contas-a-pagar"]},
  {"pdf_section_id":"8.2","menu_group":"financeiro","menu_group_label":"Financeiro","route":"/financial/receivables","doc_slug":"financeiro/contas-a-receber","status":"published","title":"Contas a Receber","summary":"Controle recebimentos, vencimentos e conciliações de receita.","tags":["receber","financeiro","titulos"],"permission_hints":["financial_movement.list"],"related":["financeiro/faturamento"]},
  {"pdf_section_id":"8.3","menu_group":"financeiro","menu_group_label":"Financeiro","route":"/financial/expenses","doc_slug":"financeiro/contas-a-pagar","status":"published","title":"Contas a Pagar","summary":"Gerencie despesas, aprovações e pagamentos com rastreabilidade.","tags":["pagar","despesas","financeiro"],"permission_hints":["financial.expenses_list"],"related":["financeiro/despesas"]},
  {"pdf_section_id":"8.4","menu_group":"financeiro","menu_group_label":"Financeiro","route":"/financial/billing","doc_slug":"financeiro/faturamento","status":"published","title":"Faturamento","summary":"Execute faturamento e acompanhe evolução de documentos emitidos.","tags":["faturamento","financeiro","documentos"],"permission_hints":["financial.billing_list"],"related":["comercial/pedidos-de-venda","financeiro/central-dfe-documentos-fiscais"]},
  {"pdf_section_id":"8.5","menu_group":"financeiro","menu_group_label":"Financeiro","route":"/financial/fiscal-documents","doc_slug":"financeiro/central-dfe-documentos-fiscais","status":"published","title":"Central DFe / Documentos Fiscais","summary":"Consulte e gerencie documentos fiscais eletrônicos centralizados.","tags":["dfe","fiscal","documentos"],"permission_hints":["fiscal_config.list_documents"],"related":["financeiro/configuracoes-fiscais"]},
  {"pdf_section_id":"8.6","menu_group":"financeiro","menu_group_label":"Financeiro","route":"/financial/fiscal-config","doc_slug":"financeiro/configuracoes-fiscais","status":"published","title":"Configurações Fiscais","summary":"Configure parâmetros fiscais usados em emissão e integração.","tags":["fiscal","configuracao","tributacao"],"permission_hints":["fiscal_config.list"],"related":["financeiro/central-dfe-documentos-fiscais","financeiro/naturezas-de-operacao-tipos-de-operacao"]},
  {"pdf_section_id":"8.7","menu_group":"financeiro","menu_group_label":"Financeiro","route":"/financial/operation-types","doc_slug":"financeiro/naturezas-de-operacao-tipos-de-operacao","status":"published","title":"Naturezas de Operação / Tipos de Operação","summary":"Defina naturezas de operação para controle tributário e fiscal.","tags":["naturezas","operacao","fiscal"],"permission_hints":["operation_type.list"],"related":["financeiro/configuracoes-fiscais"]},
  {"pdf_section_id":"8.8","menu_group":"financeiro","menu_group_label":"Financeiro","route":"/financial/expenses","doc_slug":"financeiro/despesas","status":"published","title":"Despesas","summary":"Detalhe despesas do financeiro com classificação e vencimento.","tags":["despesas","financeiro","classificacao"],"permission_hints":["financial.expenses_list"],"related":["financeiro/contas-a-pagar"]},

  {"pdf_section_id":"9.1","menu_group":"qualidade","menu_group_label":"Qualidade","route":"/quality/supplier-qualifications","doc_slug":"qualidade/qualificacao-de-fornecedores","status":"published","title":"Qualificação de Fornecedores","summary":"Avalie fornecedores com critérios de conformidade e desempenho.","tags":["qualidade","fornecedores","avaliacao"],"permission_hints":["quality.suppliers_qualification_show"],"related":["cadastros/fornecedores"]},
  {"pdf_section_id":"9.2","menu_group":"qualidade","menu_group_label":"Qualidade","route":"/quality/calibrations","doc_slug":"qualidade/calibracoes","status":"published","title":"Calibrações","summary":"Gerencie o ciclo de calibração de instrumentos e alertas de prazo.","tags":["calibracao","instrumentos","qualidade"],"permission_hints":["quality.calibrations_list"],"related":["cadastros/instrumentos"]},
  {"pdf_section_id":"9.3","menu_group":"qualidade","menu_group_label":"Qualidade","route":"/quality/non-conformities","doc_slug":"qualidade/nao-conformidades","status":"published","title":"Não Conformidades","summary":"Registre e trate não conformidades com plano de ação rastreável.","tags":["nao-conformidade","qualidade","acao-corretiva"],"permission_hints":["quality.non_conformities_list"],"related":["qualidade/qualificacao-de-fornecedores"]},

  {"pdf_section_id":"10.1","menu_group":"rh","menu_group_label":"Recursos Humanos","route":"/rh","doc_slug":"rh/dashboard-rh","status":"published","title":"Dashboard RH","summary":"Acompanhe indicadores de pessoas, ciclos e pendências de RH.","tags":["rh","dashboard","indicadores"],"permission_hints":["hr.view_module"],"related":["rh/beneficios","rh/avaliacoes-de-desempenho"]},
  {"pdf_section_id":"10.2","menu_group":"rh","menu_group_label":"Recursos Humanos","route":"/rh/benefits","doc_slug":"rh/beneficios","status":"published","title":"Benefícios","summary":"Gerencie benefícios corporativos e vínculos por colaborador.","tags":["rh","beneficios","colaboradores"],"permission_hints":["hr.manage_benefits"],"related":["rh/dashboard-rh"]},
  {"pdf_section_id":"10.3","menu_group":"rh","menu_group_label":"Recursos Humanos","route":"/rh/evaluations","doc_slug":"rh/avaliacoes-de-desempenho","status":"published","title":"Avaliações de Desempenho","summary":"Planeje ciclos, execute avaliações e acompanhe resultados.","tags":["rh","avaliacoes","desempenho"],"permission_hints":["hr.manage_evaluations"],"related":["rh/dashboard-rh"]},

  {"pdf_section_id":"11.1","menu_group":"relatorios","menu_group_label":"Relatórios","route":"/report","doc_slug":"relatorios/central-de-relatorios","status":"published","title":"Central de Relatórios","summary":"Acesse relatórios operacionais, filtros e exportações em um único ponto.","tags":["relatorios","exportacao","filtros"],"permission_hints":["report.list"],"related":["relatorios/desempenho-de-tecnicos","relatorios/relatorio-de-estoque"]},
  {"pdf_section_id":"11.2","menu_group":"relatorios","menu_group_label":"Relatórios","route":"/report/performance","doc_slug":"relatorios/desempenho-de-tecnicos","status":"published","title":"Desempenho de Técnicos","summary":"Analise produtividade técnica e indicadores de execução em campo.","tags":["relatorio","tecnicos","desempenho"],"permission_hints":["report.performance"],"related":["administracao/controle-de-produtividade"]},
  {"pdf_section_id":"11.3","menu_group":"relatorios","menu_group_label":"Relatórios","route":"/report/stock","doc_slug":"relatorios/relatorio-de-estoque","status":"published","title":"Relatório de Estoque","summary":"Monitore níveis de estoque, movimentação e cobertura de itens.","tags":["relatorio","estoque","movimentacao"],"permission_hints":["stock.stock_export"],"related":["gestao/hub-de-estoque"]},

  {"pdf_section_id":"12.1","menu_group":"administracao","menu_group_label":"Administração","route":"/user","doc_slug":"administracao/usuarios","status":"published","title":"Usuários","summary":"Cadastre usuários e administre acessos por perfil.","tags":["usuarios","acesso","administracao"],"permission_hints":["user.list"],"related":["administracao/cargos","administracao/permissoes"]},
  {"pdf_section_id":"12.2","menu_group":"administracao","menu_group_label":"Administração","route":"/user/roles","doc_slug":"administracao/cargos","status":"published","title":"Cargos","summary":"Defina cargos e responsabilidades para controle de acesso.","tags":["cargos","papeis","administracao"],"permission_hints":["role.list"],"related":["administracao/permissoes","administracao/usuarios"]},
  {"pdf_section_id":"12.3","menu_group":"administracao","menu_group_label":"Administração","route":"/config/permissions","doc_slug":"administracao/permissoes","status":"published","title":"Permissões","summary":"Configure permissões finas por módulo, função e operação.","tags":["permissoes","seguranca","admin"],"permission_hints":["config.config_permissions"],"related":["administracao/cargos","acesso-e-navegacao/sistema-de-permissoes"]},
  {"pdf_section_id":"12.4","menu_group":"administracao","menu_group_label":"Administração","route":"/productivity-dashboard","doc_slug":"administracao/controle-de-produtividade","status":"published","title":"Controle de Produtividade","summary":"Acompanhe tempo operacional e indicadores de produtividade.","tags":["produtividade","tempo","indicadores"],"permission_hints":["productivity.reports"],"related":["relatorios/desempenho-de-tecnicos"]},
  {"pdf_section_id":"12.5","menu_group":"administracao","menu_group_label":"Administração","route":"/import","doc_slug":"administracao/importacao","status":"published","title":"Importação","summary":"Importe dados em lote seguindo layout e validações do sistema.","tags":["importacao","lote","dados"],"permission_hints":["import-menu.list"],"related":["cadastros/clientes","cadastros/catalogo-de-produtos"]},
  {"pdf_section_id":"12.6","menu_group":"administracao","menu_group_label":"Administração","route":"/sla-configuration","doc_slug":"administracao/configuracao-de-sla","status":"published","title":"Configuração de SLA","summary":"Defina tempos alvo por etapa operacional para controle de OS.","tags":["sla","tempo","configuracao"],"permission_hints":["sla_configuration.list"],"related":["operacoes/ordem-de-servico","administracao/controle-de-produtividade"]}
]
